tahoe_lti/__init__.py
tahoe_lti/openedx_modules.py
tahoe_lti/processors.py
tahoe_lti/xblock_helpers.py
tahoe_lti-0.4.0.dist-info/LICENSE
tahoe_lti-0.4.0.dist-info/METADATA
tahoe_lti-0.4.0.dist-info/WHEEL
tahoe_lti-0.4.0.dist-info/top_level.txt
tahoe_lti-0.4.0.dist-info/RECORD
