Metadata-Version: 2.1
Name: tahoe-lti
Version: 0.4.0
Summary: Tahoe LTI Customizations package.
Home-page: UNKNOWN
License: UNKNOWN
Platform: UNKNOWN
License-File: LICENSE
